[
  {
    "id":1,
    "titulo":"Tutankamón",
    "descripcion":"La exhibición cuenta con más de 200 piezas provenientes de Toscana, Italia.",
    "lugar":"Portal Hidalgo núm. 4, Centro Histórico Puebla, Puebla.  ",
    "fecha":"Del 21 de agosto al 10 de diciembre, 10:00 a 21:00",
    "image":"tutankamon",
    "link":"http://dondeir.com/viajes/tutankamon-llega-a-puebla/2015/08"

  },
  {
    "id":2,
    "titulo":"Ballet Folklórico de México de Amalia Hernández",
    "descripcion":"Un espectáculo que reúne: música, danza, creatividad artística y extraordinarias",
    "lugar":"CCU BUAP",
    "fecha":"Septiembre 4, 8:00 pm ",
    "image":"ballet",
    "link":"http://148.228.60.7/CCUNueva/detalle.php?id=2012214367"

  },
  {
    "id":5,
    "titulo":"Recorre la Biblioteca Palafoxiana",
    "descripcion":"",
    "lugar":"Biblioteca Palafoxiana",
    "fecha":"2015",
    "image":"biblioteca",
    "link":"http://www.conaculta.gob.mx/estados/actividades_detalle.php?id=127144#.VekeV51_Oko"

  },
  {
    "id":4,
    "titulo":"William Kentridge: Fortuna ",
    "descripcion":"Fortuna consiste en una revisión general de la obra de William Kentridge (Johannesburgo, 1955).",
    "lugar":"Museo Amparo",
    "fecha":"del 04 de julio al 05 de octubre de 2015",
    "image":"fortuna",
    "link":"http://www.conaculta.gob.mx/estados/actividades_detalle.php?id=136244#.VekegZ1_Oko"

  },

  {
    "id":3,
    "titulo":"Noche de museos",
    "descripcion":"Este evento tiene como objetivo acercar a poblanos como a turistas nacionales y extranjeros, a la extensa oferta museística de la ciudad",
    "lugar":"Museo Regional Casa de Alfeñique, 4 Oriente 416 , Esquina con 6 Norte ",
    "fecha":"12 de septiembre de 2015",
    "image":"noche",
    "link":"http://www.conaculta.gob.mx/estados/actividades_detalle.php?id=135288#.Vekgbp1_Okp"

  }
]